{                                                                                                                                                                                                             
    "owner": {                                                                                                                                                                                                  
      "username": "tishir31",                                                                                                                                                                                   
      "email": "tishir@umich.com"                                                                                                                                                                         
    },                                                                                                                                                                                                          
    "record": {                                                                                                                                                                                                 
      "CNAME": "tishir31.github.io"                                                                                                                                                                             
    }                                                                                                                                                                                                           
  } 
