{
  "repo": "https://github.com/lverx",
  "owner": {
    "username": "lverx",
    "email": "hydrosexuallol@gmail.com"
  },
  "record": {
    "MX": [
      "ASPMX.L.GOOGLE.COM",
      "ALT1.ASPMX.L.GOOGLE.COM"
      ]
    },
  },
  "redirect_config": {
    "custom_paths": {
      "/github": "https://github.com/lverx",
      "/biz": "https://github.com/lverz",
      "/contact": "https://contact-lver.pages.dev/",
      "/site": "https://lver.link"
    },
    "redirect_paths": true
  },
  "proxied": true
}
