{
    "description": "making a cool portfolio website.",
    "repo": "https://github.com/xrap1dx?tab=repositories",
    "owner": {
        "username": "xrap1dx",
        "email": "sirrapid155@gmail.com"
    },
    "record": {
        "A": [
            "69.30.249.53"
        ],
        "MX": [
            "mx1.improvmx.com",
            "mx2.improvmx.com"
        ],
        "TXT": [
            "v=spf1 include:spf.improvmx.com ~all",
            "zoho-verification=zb43908801.zmverify.zoho.eu"
        ]
    }
}
